hubapi/__init__.py
hubapi-1.0.0.dist-info/LICENSE
hubapi-1.0.0.dist-info/METADATA
hubapi-1.0.0.dist-info/WHEEL
hubapi-1.0.0.dist-info/top_level.txt
hubapi-1.0.0.dist-info/RECORD
