Metadata-Version: 2.1
Name: hubapi
Version: 1.0.0
Summary: package for hubspot api
Home-page: https://github.com/
Author: emalashenkov
Author-email: egor_malashenkov@mail.ru
License: UNKNOWN
Project-URL: Documentation, https://github.com/
Platform: UNKNOWN
Classifier: Programming Language :: Python :: 3.9
Classifier: License :: OSI Approved :: MIT License
Classifier: Operating System :: OS Independent
Requires-Python: >=3.7
License-File: LICENSE
Requires-Dist: requests (>=2.25.1)
